main.py
csv2db/__init__.py
csv2db/config.py
csv2db/constants.py
csv2db/functions.py
csv2db-1.6.1.dist-info/LICENSE
csv2db-1.6.1.dist-info/METADATA
csv2db-1.6.1.dist-info/WHEEL
csv2db-1.6.1.dist-info/entry_points.txt
csv2db-1.6.1.dist-info/top_level.txt
csv2db-1.6.1.dist-info/RECORD
