Metadata-Version: 2.1
Name: csv2db
Version: 1.6.1
Summary: The CSV to database command line loader.
Author: Gerald Venzl
Maintainer: Gerald Venzl
Project-URL: Documentation, https://github.com/csv2db/csv2db/wiki
Project-URL: Homepage, https://csv2db.github.io/
Project-URL: Issues, https://github.com/csv2db/csv2db/issues
Project-URL: Source, https://github.com/csv2db/csv2db
Classifier: Development Status :: 5 - Production/Stable
Classifier: Environment :: Console
Classifier: Intended Audience :: End Users/Desktop
Classifier: License :: OSI Approved :: Apache Software License
Classifier: Operating System :: OS Independent
Classifier: Programming Language :: Python :: 3
Classifier: Programming Language :: Python :: 3.8
Classifier: Programming Language :: Python :: 3.9
Classifier: Programming Language :: Python :: 3.10
Classifier: Programming Language :: Python :: 3.11
Classifier: Programming Language :: Python :: 3.12
Classifier: Programming Language :: Python :: 3 :: Only
Classifier: Topic :: Database
Classifier: Topic :: Utilities
Requires-Python: >=3.8
License-File: LICENSE
Requires-Dist: oracledb >=2.0.0
Requires-Dist: mysql-connector-python >=8.0.13
Requires-Dist: psycopg[binary] >=3.1.9
Requires-Dist: pymssql >=2.1.4
